anyserve/__init__.py
anyserve/_core.cpython-313-darwin.so
anyserve/_proto/__init__.py
anyserve/_proto/grpc_predict_v2_pb2.py
anyserve/_proto/grpc_predict_v2_pb2_grpc.py
anyserve/_proto/worker_management_pb2.py
anyserve/_proto/worker_management_pb2_grpc.py
anyserve/builtins/__init__.py
anyserve/builtins/llamacpp/__init__.py
anyserve/builtins/llamacpp/app.py
anyserve/builtins/llamacpp/config.py
anyserve/builtins/llamacpp/engine.py
anyserve/builtins/llamacpp/openai_compat/__init__.py
anyserve/builtins/llamacpp/openai_compat/kserve_client.py
anyserve/builtins/llamacpp/openai_compat/server.py
anyserve/builtins/llamacpp/openai_server.py
anyserve/cli/__init__.py
anyserve/cli/main.py
anyserve/cli/run.py
anyserve/cli/serve.py
anyserve/kserve.py
anyserve/objects/__init__.py
anyserve/objects/store.py
anyserve/worker/__init__.py
anyserve/worker/__main__.py
anyserve/worker/client.py
anyserve/worker/loader.py
anyserve/worker/proto/__init__.py
anyserve/worker/proto/grpc_predict_v2_pb2.py
anyserve/worker/proto/grpc_predict_v2_pb2_grpc.py
anyserve/worker/proto/worker_management_pb2.py
anyserve/worker/proto/worker_management_pb2_grpc.py
anyserve-0.1.2.data/scripts/anyserve_agent
anyserve-0.1.2.dist-info/METADATA
anyserve-0.1.2.dist-info/WHEEL
anyserve-0.1.2.dist-info/entry_points.txt
anyserve-0.1.2.dist-info/RECORD
