Metadata-Version: 2.2
Name: anyserve
Version: 0.1.2
Summary: anyServe - Capability-Oriented Serving Runtime for LLM inference
Author-Email: simpx <simpxx@gmail.com>
Requires-Python: >=3.11
Requires-Dist: fastapi>=0.109.0
Requires-Dist: uvicorn>=0.27.0
Requires-Dist: grpcio>=1.60.0
Requires-Dist: grpcio-tools>=1.60.0
Requires-Dist: requests>=2.31.0
Requires-Dist: click>=8.0.0
Requires-Dist: httpx>=0.25.0
Requires-Dist: pyyaml>=6.0
Requires-Dist: pydantic>=2.0.0
Requires-Dist: llama-cpp-python>=0.2.0
Provides-Extra: dev
Requires-Dist: pytest>=7.0.0; extra == "dev"
Requires-Dist: pytest-asyncio>=0.21.0; extra == "dev"
Requires-Dist: pytest-cov>=4.0.0; extra == "dev"
